<?xml version="1.0" encoding="UTF-8"?><?xml-stylesheet type='text/xsl' href='_UpgradeReport_Files/UpgradeReport.xslt'?><UpgradeLog>
<Properties><Property Name="Solution" Value="DeployAddIn">
</Property><Property Name="Solution File" Value="C:\code\deployaddin\DeployAddIn.sln">
</Property><Property Name="Date" Value="07 May 2007">
</Property><Property Name="Time" Value="07:58">
</Property></Properties><Event ErrorLevel="0" Project="DeployAddIn" Source="DeployAddIn.csproj" Description="Project converted successfully">
</Event><Event ErrorLevel="3" Project="DeployAddIn" Source="DeployAddIn.csproj" Description="Converted">
</Event><Event ErrorLevel="0" Project="" Source="DeployAddIn.sln" Description="Solution converted successfully">
</Event><Event ErrorLevel="3" Project="" Source="DeployAddIn.sln" Description="Converted">
</Event><Event ErrorLevel="0" Project="DeployAddIn" Source="DeployAddIn.csproj" Description="Scan complete: Upgrade not required for project files.">
</Event></UpgradeLog>